eth_tester/__init__.py
eth_tester/constants.py
eth_tester/exceptions.py
eth_tester/main.py
eth_tester/rpc.py
eth_tester/backends/__init__.py
eth_tester/backends/base.py
eth_tester/backends/mock/__init__.py
eth_tester/backends/mock/factory.py
eth_tester/backends/mock/main.py
eth_tester/backends/mock/serializers.py
eth_tester/backends/pyethereum/__init__.py
eth_tester/backends/pyethereum/utils.py
eth_tester/backends/pyethereum/v20.py
eth_tester/backends/pyethereum/v16/__init__.py
eth_tester/backends/pyethereum/v16/main.py
eth_tester/backends/pyethereum/v16/serializers.py
eth_tester/backends/pyethereum/v16/validation.py
eth_tester/normalization/__init__.py
eth_tester/normalization/base.py
eth_tester/normalization/common.py
eth_tester/normalization/default.py
eth_tester/normalization/inbound.py
eth_tester/normalization/outbound.py
eth_tester/utils/__init__.py
eth_tester/utils/accounts.py
eth_tester/utils/backend_testing.py
eth_tester/utils/emitter_contract.py
eth_tester/utils/encoding.py
eth_tester/utils/filters.py
eth_tester/utils/formatting.py
eth_tester/utils/jacobian.py
eth_tester/utils/math_contract.py
eth_tester/utils/module_loading.py
eth_tester/utils/secp256k1.py
eth_tester/utils/six/__init__.py
eth_tester/utils/six/py2.py
eth_tester/utils/six/py3.py
eth_tester/validation/__init__.py
eth_tester/validation/base.py
eth_tester/validation/common.py
eth_tester/validation/default.py
eth_tester/validation/inbound.py
eth_tester/validation/outbound.py
ethereum_tester-0.1.0a6.dist-info/DESCRIPTION.rst
ethereum_tester-0.1.0a6.dist-info/METADATA
ethereum_tester-0.1.0a6.dist-info/RECORD
ethereum_tester-0.1.0a6.dist-info/WHEEL
ethereum_tester-0.1.0a6.dist-info/metadata.json
ethereum_tester-0.1.0a6.dist-info/top_level.txt
