Metadata-Version: 2.0
Name: ethereum-tester
Version: 0.1.0a6
Summary: Tools for testing Ethereum applications.
Home-page: https://github.com/pipermerriam/ethereum-tester
Author: Piper Merriam
Author-email: pipermerriam@gmail.com
License: MIT
Keywords: ethereum
Platform: UNKNOWN
Classifier: Development Status :: 2 - Pre-Alpha
Classifier: Intended Audience :: Developers
Classifier: License :: OSI Approved :: MIT License
Classifier: Natural Language :: English
Classifier: Programming Language :: Python :: 2
Classifier: Programming Language :: Python :: 2.7
Classifier: Programming Language :: Python :: 3
Classifier: Programming Language :: Python :: 3.4
Classifier: Programming Language :: Python :: 3.5
Requires-Dist: cytoolz (==0.8.2)
Requires-Dist: ethereum-utils (>=0.3.1)
Requires-Dist: rlp (==0.5.1)
Requires-Dist: semantic-version (>=2.6.0)
Provides-Extra: pyethereum16
Requires-Dist: ethereum (>=1.6.0,<2.0.0); extra == 'pyethereum16'
